taxim/__init__.py
taxim/calibration.py
taxim/taxim.py
taxim/taxim_impl.py
taxim/taxim_jax.py
taxim/taxim_torch.py
taxim/calib/gelsight/dataPack.npz
taxim/calib/gelsight/gelmap.npy
taxim/calib/gelsight/params.json
taxim/calib/gelsight/polycalib.npz
taxim/calib/gelsight/shadowTable.npz
taxim/calib/gelsight_mini/dataPack.npz
taxim/calib/gelsight_mini/gelmap.npy
taxim/calib/gelsight_mini/params.json
taxim/calib/gelsight_mini/polycalib.npz
taxim/calib/gelsight_mini/shadowTable.npz
taxim-1.4.1.dist-info/licenses/LICENSE
taxim-1.4.1.dist-info/METADATA
taxim-1.4.1.dist-info/WHEEL
taxim-1.4.1.dist-info/top_level.txt
taxim-1.4.1.dist-info/RECORD
