Metadata-Version: 2.4
Name: taxim
Version: 1.4.1
Summary: GPU accelerated implementation of the Taxim simulator.
Author-email: Tim Schneider <tim@robot-learning.de>
License: MIT
Project-URL: homepage, https://github.com/TimSchneider42/taxim
License-File: LICENSE
Requires-Dist: numpy
Provides-Extra: all
Requires-Dist: torch; extra == "all"
Requires-Dist: torchvision; extra == "all"
Requires-Dist: torch-scatter; extra == "all"
Requires-Dist: jax[cuda12]; extra == "all"
Requires-Dist: matplotlib; extra == "all"
Provides-Extra: torch
Requires-Dist: torch; extra == "torch"
Requires-Dist: torch-scatter; extra == "torch"
Requires-Dist: torchvision; extra == "torch"
Provides-Extra: jax
Requires-Dist: jax[cuda12]; extra == "jax"
Provides-Extra: jax-cpu
Requires-Dist: jax; extra == "jax-cpu"
Provides-Extra: examples
Requires-Dist: matplotlib; extra == "examples"
Dynamic: license-file
